djorm_ext_pgfulltext-0.9.3.dist-info/DESCRIPTION.rst
djorm_ext_pgfulltext-0.9.3.dist-info/METADATA
djorm_ext_pgfulltext-0.9.3.dist-info/metadata.json
djorm_ext_pgfulltext-0.9.3.dist-info/pbr.json
djorm_ext_pgfulltext-0.9.3.dist-info/RECORD
djorm_ext_pgfulltext-0.9.3.dist-info/top_level.txt
djorm_ext_pgfulltext-0.9.3.dist-info/WHEEL
djorm_pgfulltext/__init__.py
djorm_pgfulltext/fields.py
djorm_pgfulltext/gis.py
djorm_pgfulltext/models.py
djorm_pgfulltext/management/__init__.py
djorm_pgfulltext/management/commands/__init__.py
djorm_pgfulltext/management/commands/update_search_field.py
djorm_pgfulltext/tests/__init__.py
djorm_pgfulltext/tests/models.py
djorm_pgfulltext/tests/migrations/0001_initial.py
djorm_pgfulltext/tests/migrations/0001_initial.sql
djorm_pgfulltext/tests/migrations/__init__.py
djorm_pgfulltext/tests/sql/person.postgresql_psycopg2.sql
