Metadata-Version: 2.0
Name: djorm-ext-pgfulltext
Version: 0.9.3
Summary: PostgreSQL Full Text Search integration with django orm.
Home-page: https://github.com/linuxlewis/djorm-ext-pgfulltext
Author: Lovely Team
Author-email: engineering@livelovely.com
License: BSD
Platform: UNKNOWN
Classifier: "Development Status :: 5 - Production/Stable",
Classifier: "Operating System :: OS Independent",
Classifier: "Environment :: Web Environment",
Classifier: "Framework :: Django",
Classifier: "License :: OSI Approved :: BSD License",
Classifier: "Intended Audience :: Developers",
Classifier: "Programming Language :: Python",
Classifier: "Programming Language :: Python :: 2",
Classifier: "Programming Language :: Python :: 2.7",
Classifier: "Programming Language :: Python :: 3",
Classifier: "Programming Language :: Python :: 3.2",
Classifier: "Programming Language :: Python :: 3.3",
Classifier: "Programming Language :: Python :: 3.4",
Classifier: "Topic :: Software Development :: Libraries",
Classifier: "Topic :: Utilities",
Requires-Dist: django (>1.3)
Requires-Dist: psycopg2 (>2.0)
